<?xml version="1.0" encoding="UTF-8" ?>
<!DOCTYPE hibernate-mapping PUBLIC
        "-//Hibernate/Hibernate mapping DTD 3.0//EN"
        "http://www.hibernate.org/dtd/hibernate-mapping-3.0.dtd">
<hibernate-mapping>
    <class name="Book" table="book">
        <id name="id" column="book_id"></id>
        <property name="title" column="Title"/>
        <property name="description" column="DESCRIPTION"/>
        <property name="published" column="PUBLISHED"/>
        <many-to-one name="author" class="Author" column="author_id" unique="true" not-null="true" cascade="all"/>
    </class>
</hibernate-mapping>